jwt_smithy/__main__.py
jwt_smithy/ecdsa.py
jwt_smithy/file_saver.py
jwt_smithy/rsa.py
jwt_smithy/shmac.py
jwt_smithy-1.1.0.dist-info/entry_points.txt
jwt_smithy-1.1.0.dist-info/LICENSE
jwt_smithy-1.1.0.dist-info/WHEEL
jwt_smithy-1.1.0.dist-info/METADATA
jwt_smithy-1.1.0.dist-info/RECORD
